fairfru/__init__.py
fairfru/main.py
fairfru/utils/FRSpy.py
fairfru/utils/__init__.py
fairfru/utils/h5file_create_array.py
fairfru-1.9.2.dist-info/licenses/LICENSE
fairfru-1.9.2.dist-info/METADATA
fairfru-1.9.2.dist-info/WHEEL
fairfru-1.9.2.dist-info/top_level.txt
fairfru-1.9.2.dist-info/RECORD
