Metadata-Version: 2.4
Name: fairfru
Version: 1.9.2
Summary: A bias measure based on the fuzzy rough set theory
Author-email: Lisa Koutsoviti <liza.koutsoviti@gmail.com>, Gonzalo Napoles <G.R.Napoles@tilburguniversity.edu>
License-Expression: MIT
Project-URL: Homepage, https://github.com/LisaKouts/FRUbias
Project-URL: Issues, https://github.com/LisaKouts/FRUbias/issues
Classifier: Programming Language :: Python :: 3
Classifier: Operating System :: OS Independent
Requires-Python: >=3.8
License-File: LICENSE
Dynamic: license-file
